MANIFEST.in
README.md
setup.py
custom_admin/__init__.py
custom_admin/admin.py
custom_admin/apps.py
custom_admin/config.py
custom_admin/forms.py
custom_admin/helpers.py
custom_admin/inlines.py
custom_admin/list_filters.py
custom_admin/models.py
custom_admin/urls.py
custom_admin/utility_functions.py
custom_admin/utils.py
custom_admin/view_bases.py
custom_admin/views.py
custom_admin/widgets.py
custom_admin.egg-info/PKG-INFO
custom_admin.egg-info/SOURCES.txt
custom_admin.egg-info/dependency_links.txt
custom_admin.egg-info/requires.txt
custom_admin.egg-info/top_level.txt
custom_admin/management/__init__.py
custom_admin/management/commands/__init__.py
custom_admin/migrations/0001_initial.py
custom_admin/migrations/__init__.py
custom_admin/static/admin/css/custom-admin-style.css
custom_admin/static/admin/css/custom-admin-style.min.css
custom_admin/static/admin/fontawesome/css/all.css
custom_admin/static/admin/fontawesome/css/all.min.css
custom_admin/static/admin/fontawesome/css/all.min.min.css
custom_admin/static/admin/fontawesome/css/all.min.min.min.css
custom_admin/static/admin/fontawesome/css/all.min.min.min.min.css
custom_admin/static/admin/fontawesome/css/brands.css
custom_admin/static/admin/fontawesome/css/brands.min.css
custom_admin/static/admin/fontawesome/css/brands.min.min.css
custom_admin/static/admin/fontawesome/css/brands.min.min.min.css
custom_admin/static/admin/fontawesome/css/brands.min.min.min.min.css
custom_admin/static/admin/fontawesome/css/fontawesome.css
custom_admin/static/admin/fontawesome/css/fontawesome.min.css
custom_admin/static/admin/fontawesome/css/fontawesome.min.min.css
custom_admin/static/admin/fontawesome/css/regular.css
custom_admin/static/admin/fontawesome/css/regular.min.css
custom_admin/static/admin/fontawesome/css/regular.min.min.css
custom_admin/static/admin/fontawesome/css/regular.min.min.min.css
custom_admin/static/admin/fontawesome/css/regular.min.min.min.min.css
custom_admin/static/admin/fontawesome/css/solid.css
custom_admin/static/admin/fontawesome/css/solid.min.css
custom_admin/static/admin/fontawesome/css/solid.min.min.css
custom_admin/static/admin/fontawesome/css/solid.min.min.min.css
